nucypher_ops/__about__.py
nucypher_ops/__init__.py
nucypher_ops/constants.py
nucypher_ops/cli/ethereum.py
nucypher_ops/cli/main.py
nucypher_ops/cli/namespaces.py
nucypher_ops/cli/nodes.py
nucypher_ops/cli/porter.py
nucypher_ops/cli/ursula.py
nucypher_ops/ops/ansible_utils.py
nucypher_ops/ops/contracts.py
nucypher_ops/ops/fleet_ops.py
nucypher_ops/ops/keygen.py
nucypher_ops/playbooks/backup_remote_workers.yml
nucypher_ops/playbooks/basic_install.yml
nucypher_ops/playbooks/get_workers_status.yml
nucypher_ops/playbooks/restore_ursula_from_backup.yml
nucypher_ops/playbooks/setup_porter.yml
nucypher_ops/playbooks/setup_remote_workers.yml
nucypher_ops/playbooks/setup_standalone_geth_node.yml
nucypher_ops/playbooks/stop_remote_workers.yml
nucypher_ops/playbooks/update_remote_workers.yml
nucypher_ops/playbooks/include/backup_ursula_data.yml
nucypher_ops/playbooks/include/check_running_ursula.yml
nucypher_ops/playbooks/include/init_ursula.yml
nucypher_ops/playbooks/include/init_worker.yml
nucypher_ops/playbooks/include/install_geth.yml
nucypher_ops/playbooks/include/install_porter.yml
nucypher_ops/playbooks/include/print_ursula_log.yml
nucypher_ops/playbooks/include/run_external_geth.yml
nucypher_ops/playbooks/include/run_geth.yml
nucypher_ops/playbooks/include/run_porter.yml
nucypher_ops/playbooks/include/run_ursula.yml
nucypher_ops/playbooks/include/setup_docker.yml
nucypher_ops/playbooks/include/setup_user.yml
nucypher_ops/playbooks/include/stop_containers.yml
nucypher_ops/playbooks/include/update_existing_ursula.yml
nucypher_ops/templates/ethereum_inventory.mako
nucypher_ops/templates/porter_inventory.mako
nucypher_ops/templates/ursula_inventory.mako
nucypher_ops-0.11.2.dist-info/LICENSE
nucypher_ops-0.11.2.dist-info/METADATA
nucypher_ops-0.11.2.dist-info/WHEEL
nucypher_ops-0.11.2.dist-info/entry_points.txt
nucypher_ops-0.11.2.dist-info/top_level.txt
nucypher_ops-0.11.2.dist-info/RECORD
