Metadata-Version: 2.1
Name: nucypher-ops
Version: 0.11.2
Summary: Install and management tools for a proxy re-encryption network to empower privacy in decentralized systems.
Home-page: https://github.com/nucypher/nucypher-ops
Author: NuCypher
Author-email: dev@nucypher.com
License: GNU Affero General Public License, Version 3
License-File: LICENSE
Requires-Dist: click
Requires-Dist: colorama
Requires-Dist: ansible
Requires-Dist: hdwallet
Requires-Dist: mako
Requires-Dist: requests
Requires-Dist: maya
Requires-Dist: appdirs
